Workbook

Sheet README
A1: Value-at-Stake Model - Zellis Rightsizing Diagnostic
A3: How to use: every white cell is a live formula. Change assumptions on 'Assumptions' only.
A4: All money figures in GBP thousands (GBP k) unless marked GBP m.
A6: Tabs:
A7: Inputs_Sourced - verified figures from filed accounts (each with source reference)
A8: Assumptions - the only place to change drivers; peer stats computed live from Inputs_Sourced
A9: Model - dual-method sizing (A: ratio-gap x revenue; B: headcount delta x cost/FTE)
A10: Scenarios - Low / Base / High anchored to peer percentiles (QUARTILE formulas)
A11: Sensitivity - 2-way grid: % of gap closed x cost-to-implement (all formulas)
A13: Rebuild: python data/build_model.py
A14: Data log: data/data-log.md | dataset: data/financials.csv | findings: analysis/step-4-analysis.md
A16: Caveats: entity-vs-group basis; OneAdvanced continuing ops; Access roll-up (M&A-driven growth);
A17: restatements; IRIS group accounts via PARENT_ACC filings; Sage excluded as listed anchor.

Sheet Inputs_Sourced
A1: Sourced data - filed accounts (GBP k; headcount = average monthly FTE)
A3: Company | B3: Role | C3: FY | D3: Period end | E3: Revenue GBP k | F3: Staff costs GBP k | G3: Avg headcount | H3: Source | I3: In peer stats
A4: Access UK Ltd | B4: peer | C4: FY2021 | D4: 44377 | E4: 317647 | F4: 127704 | G4: 2255 | H4: see data/financials.csv + data/data-log.md | J4: =AND($B4="peer",COUNTIFS($A$4:$A$100,$A4,$C$4:$C$100,">"&$C4)=0)
A5: Access UK Ltd | B5: peer | C5: FY2022 | D5: 44742 | E5: 434381 | F5: 193215 | G5: 3009 | H5: see data/financials.csv + data/data-log.md | J5: =AND($B5="peer",COUNTIFS($A$4:$A$100,$A5,$C$4:$C$100,">"&$C5)=0)
A6: Access UK Ltd | B6: peer | C6: FY2023 | D6: 45107 | E6: 581466 | F6: 236051 | G6: 4428 | H6: see data/financials.csv + data/data-log.md | J6: =AND($B6="peer",COUNTIFS($A$4:$A$100,$A6,$C$4:$C$100,">"&$C6)=0)
A7: Access UK Ltd | B7: peer | C7: FY2024 | D7: 45473 | E7: 708813 | F7: 265270 | G7: 4429 | H7: see data/financials.csv + data/data-log.md | J7: =AND($B7="peer",COUNTIFS($A$4:$A$100,$A7,$C$4:$C$100,">"&$C7)=0)
A8: Access UK Ltd | B8: peer | C8: FY2025 | D8: 45838 | E8: 751022 | F8: 300058 | G8: 4591 | H8: see data/financials.csv + data/data-log.md | J8: =AND($B8="peer",COUNTIFS($A$4:$A$100,$A8,$C$4:$C$100,">"&$C8)=0)
A9: IRIS Business Software Limited (group) | B9: peer | C9: FY2023 | D9: 45046 | E9: 319080 | F9: 131648 | G9: 2638 | H9: see data/financials.csv + data/data-log.md | J9: =AND($B9="peer",COUNTIFS($A$4:$A$100,$A9,$C$4:$C$100,">"&$C9)=0)
A10: IRIS Business Software Limited (group) | B10: peer | C10: FY2024 | D10: 45412 | E10: 373544 | F10: 161282 | G10: 2986 | H10: see data/financials.csv + data/data-log.md | J10: =AND($B10="peer",COUNTIFS($A$4:$A$100,$A10,$C$4:$C$100,">"&$C10)=0)
A11: OneAdvanced Group Limited | B11: peer | C11: FY2022 | D11: 44620 | E11: 316494 | F11: 132593 | G11: 2676 | H11: see data/financials.csv + data/data-log.md | J11: =AND($B11="peer",COUNTIFS($A$4:$A$100,$A11,$C$4:$C$100,">"&$C11)=0)
A12: OneAdvanced Group Limited | B12: peer | C12: FY2023 | D12: 44985 | E12: 321708 | F12: 150689 | G12: 2960 | H12: see data/financials.csv + data/data-log.md | J12: =AND($B12="peer",COUNTIFS($A$4:$A$100,$A12,$C$4:$C$100,">"&$C12)=0)
A13: OneAdvanced Group Limited | B13: peer | C13: FY2024 | D13: 45351 | E13: 320148 | F13: 143607 | G13: 2753 | H13: see data/financials.csv + data/data-log.md | J13: =AND($B13="peer",COUNTIFS($A$4:$A$100,$A13,$C$4:$C$100,">"&$C13)=0)
A14: OneAdvanced Group Limited | B14: peer | C14: FY2025 | D14: 45716 | E14: 308959 | F14: 113549 | G14: 2283 | H14: see data/financials.csv + data/data-log.md | J14: =AND($B14="peer",COUNTIFS($A$4:$A$100,$A14,$C$4:$C$100,">"&$C14)=0)
A15: Zellis Holdings Limited | B15: target | C15: FY2021 | D15: 44316 | E15: 159703 | F15: 92776 | G15: 2221 | H15: see data/financials.csv + data/data-log.md | J15: =AND($B15="peer",COUNTIFS($A$4:$A$100,$A15,$C$4:$C$100,">"&$C15)=0)
... A19: Zellis Holdings Limited | B19: target | C19: FY2025 | D19: 45777 | E19: 261068 | F19: 136488 | G19: 2655 | H19: see data/financials.csv + data/data-log.md | J19: =AND($B19="peer",COUNTIFS($A$4:$A$100,$A19,$C$4:$C$100,">"&$C19)=0)
A21: Sage Group plc (public anchor) excluded from peer stats - listed company, different scale.

Sheet Assumptions
A1: Assumptions - the only tab to edit
A2: Yellow cells = editable judgement. White = computed live from Inputs_Sourced.
A4: TARGET (Zellis Holdings, group) - FY2025
A5: Target revenue (GBP k) | B5: =INDEX(Inputs_Sourced!$E:$E,MATCH(1,(Inputs_Sourced!$B$4:$B$100="target")*(Inputs_Sourced!$C$4:$C$100="FY2025")*(Inputs_Sourced!$A$4:$A$100="Zellis Holdings Limited"),0))
A6: Target average headcount | B6: =INDEX(Inputs_Sourced!$G:$G,MATCH(1,(Inputs_Sourced!$B$4:$B$100="target")*(Inputs_Sourced!$C$4:$C$100="FY2025")*(Inputs_Sourced!$A$4:$A$100="Zellis Holdings Limited"),0))
A7: Target staff costs (GBP k) | B7: =INDEX(Inputs_Sourced!$F:$F,MATCH(1,(Inputs_Sourced!$B$4:$B$100="target")*(Inputs_Sourced!$C$4:$C$100="FY2025")*(Inputs_Sourced!$A$4:$A$100="Zellis Holdings Limited"),0))
A8: Target staff cost per FTE (GBP k) | B8: =B7/B6
A9: Target staff cost as % of revenue | B9: =B7/B5
A10: Target revenue per FTE (GBP k) | B10: =B5/B6
A12: PEER STATS (PE peers only; computed live)
A13: Peer median revenue per FTE (GBP k) | B13: =MEDIAN(IF(Inputs_Sourced!$B$4:$B$100="peer",IF(Inputs_Sourced!$J$4:$J$100=TRUE,Inputs_Sourced!$E$4:$E$100/Inputs_Sourced!$G$4:$G$100)))
A14: Peer 25th percentile revenue per FTE | B14: =QUARTILE(IF(Inputs_Sourced!$B$4:$B$100="peer",IF(Inputs_Sourced!$J$4:$J$100=TRUE,Inputs_Sourced!$E$4:$E$100/Inputs_Sourced!$G$4:$G$100)),1)
A15: Peer 75th percentile revenue per FTE | B15: =QUARTILE(IF(Inputs_Sourced!$B$4:$B$100="peer",IF(Inputs_Sourced!$J$4:$J$100=TRUE,Inputs_Sourced!$E$4:$E$100/Inputs_Sourced!$G$4:$G$100)),3)
A16: Peer median staff cost as % of revenue | B16: =MEDIAN(IF(Inputs_Sourced!$B$4:$B$100="peer",IF(Inputs_Sourced!$J$4:$J$100=TRUE,Inputs_Sourced!$F$4:$F$100/Inputs_Sourced!$E$4:$E$100)))
A17: Peer median staff cost per FTE (GBP k) | B17: =MEDIAN(IF(Inputs_Sourced!$B$4:$B$100="peer",IF(Inputs_Sourced!$J$4:$J$100=TRUE,Inputs_Sourced!$F$4:$F$100/Inputs_Sourced!$G$4:$G$100)))
A19: SCENARIO JUDGEMENTS (editable)
A20: Low: fraction of gap to median closed | B20: 0.5
A21: Base: fraction of gap to median closed | B21: 1
A22: High: multiplier on median rev/FTE (1.10 = 10% beyond) | B22: 1.1
A23: Cost to implement (% of annualised benefit, one-off) | B23: 0.25
A24: Benefits realised in year 1 (%) | B24: 0.6
A25: Anchors follow the peer DISTRIBUTION (25th/median/75th), not arbitrary %s.

Sheet Model
A1: Dual-method value-at-stake sizing (Base case: close gap to peer median)
A3: METHOD A - staff-cost-ratio gap x revenue
A4: Target staff cost ratio | B4: =Assumptions!B9
A5: Peer median staff cost ratio | B5: =Assumptions!B16
A6: Ratio gap (target - median) | B6: =B4-B5
A7: Target revenue (GBP k) | B7: =Assumptions!B5
A8: VALUE AT STAKE - Method A (GBP k) | B8: =B6*B7
A10: METHOD B - headcount delta x cost per FTE
A11: Target headcount | B11: =Assumptions!B6
A12: Headcount implied at peer median rev/FTE | B12: =Assumptions!B5/Assumptions!B13
A13: Headcount delta (target - implied) | B13: =B11-B12
A14: Target staff cost per FTE (GBP k) | B14: =Assumptions!B8
A15: VALUE AT STAKE - Method B (GBP k) | B15: =B13*B14
A17: CROSS-CHECK
A18: |A-B| as % of Method A (investigate if >20%) | B18: =ABS(B8-B15)/B8
A19: A prices the gap off the cost ratio; B off the headcount implied by peer productivity.
A21: YEAR-1 VIEW (phasing)
A22: Benefits realised in year 1 | B22: =Assumptions!B24
A23: Year-1 gross benefit (average of methods, phased) | B23: =(B8+B15)/2*B22
A24: One-off implementation cost | B24: =(B8+B15)/2*Assumptions!B23
A25: Year-1 net impact (GBP k) | B25: =B23-B24

Sheet Scenarios
A1: Scenarios - anchored to the peer distribution
A3: Scenario | B3: Target rev/FTE assumption (GBP k) | C3: Implied staff ratio | D3: Ratio-route benefit (GBP k) | E3: Headcount-route benefit (GBP k) | F3: Average annual benefit (GBP k)
A4: Low | B4: =Assumptions!B10+(Assumptions!B13-Assumptions!B10)*Assumptions!B20 | C4: =Assumptions!$B$7/(Assumptions!$B$6*B4) | D4: =(Assumptions!$B$9-C4)*Assumptions!$B$5 | E4: =(Assumptions!$B$6-Assumptions!$B$5/B4)*Assumptions!$B$8 | F4: =(D4+E4)/2
A5: Base | B5: =Assumptions!B10+(Assumptions!B13-Assumptions!B10)*Assumptions!B21 | C5: =Assumptions!$B$7/(Assumptions!$B$6*B5) | D5: =(Assumptions!$B$9-C5)*Assumptions!$B$5 | E5: =(Assumptions!$B$6-Assumptions!$B$5/B5)*Assumptions!$B$8 | F5: =(D5+E5)/2
A6: High | B6: =Assumptions!B10+(Assumptions!B15-Assumptions!B10)*Assumptions!B22 | C6: =Assumptions!$B$7/(Assumptions!$B$6*B6) | D6: =(Assumptions!$B$9-C6)*Assumptions!$B$5 | E6: =(Assumptions!$B$6-Assumptions!$B$5/B6)*Assumptions!$B$8 | F6: =(D6+E6)/2
A8: Low/High follow the peer IQR (25th/75th percentile of revenue per FTE), not arbitrary choices.
A9: ="Peer 25th pct: "&TEXT(Assumptions!B14,"0.0")&" | Median: "&TEXT(Assumptions!B13,"0.0")&" | 75th pct: "&TEXT(Assumptions!B15,"0.0")

Sheet Sensitivity
A1: Sensitivity: net year-1 EBITDA impact (GBP k)
A2: Rows = % of productivity gap closed. Columns = cost-to-implement as % of annualised benefit.
A4: gap closed \ cost% | B4: 0.1 | C4: 0.2 | D4: 0.3 | E4: 0.4 | F4: 0.5
A5: 0.25 | B5: =(Assumptions!$B$13-Assumptions!$B$10)*$A5*Assumptions!$B$6*Assumptions!$B$24*(1-B$4) | C5: =(Assumptions!$B$13-Assumptions!$B$10)*$A5*Assumptions!$B$6*Assumptions!$B$24*(1-C$4) | D5: =(Assumptions!$B$13-Assumptions!$B$10)*$A5*Assumptions!$B$6*Assumptions!$B$24*(1-D$4) | E5: =(Assumptions!$B$13-Assumptions!$B$10)*$A5*Assumptions!$B$6*Assumptions!$B$24*(1-E$4) | F5: =(Assumptions!$B$13-Assumptions!$B$10)*$A5*Assumptions!$B$6*Assumptions!$B$24*(1-F$4)
A6: 0.5 | B6: =(Assumptions!$B$13-Assumptions!$B$10)*$A6*Assumptions!$B$6*Assumptions!$B$24*(1-B$4) | C6: =(Assumptions!$B$13-Assumptions!$B$10)*$A6*Assumptions!$B$6*Assumptions!$B$24*(1-C$4) | D6: =(Assumptions!$B$13-Assumptions!$B$10)*$A6*Assumptions!$B$6*Assumptions!$B$24*(1-D$4) | E6: =(Assumptions!$B$13-Assumptions!$B$10)*$A6*Assumptions!$B$6*Assumptions!$B$24*(1-E$4) | F6: =(Assumptions!$B$13-Assumptions!$B$10)*$A6*Assumptions!$B$6*Assumptions!$B$24*(1-F$4)
A7: 0.75 | B7: =(Assumptions!$B$13-Assumptions!$B$10)*$A7*Assumptions!$B$6*Assumptions!$B$24*(1-B$4) | C7: =(Assumptions!$B$13-Assumptions!$B$10)*$A7*Assumptions!$B$6*Assumptions!$B$24*(1-C$4) | D7: =(Assumptions!$B$13-Assumptions!$B$10)*$A7*Assumptions!$B$6*Assumptions!$B$24*(1-D$4) | E7: =(Assumptions!$B$13-Assumptions!$B$10)*$A7*Assumptions!$B$6*Assumptions!$B$24*(1-E$4) | F7: =(Assumptions!$B$13-Assumptions!$B$10)*$A7*Assumptions!$B$6*Assumptions!$B$24*(1-F$4)
A8: 1 | B8: =(Assumptions!$B$13-Assumptions!$B$10)*$A8*Assumptions!$B$6*Assumptions!$B$24*(1-B$4) | C8: =(Assumptions!$B$13-Assumptions!$B$10)*$A8*Assumptions!$B$6*Assumptions!$B$24*(1-C$4) | D8: =(Assumptions!$B$13-Assumptions!$B$10)*$A8*Assumptions!$B$6*Assumptions!$B$24*(1-D$4) | E8: =(Assumptions!$B$13-Assumptions!$B$10)*$A8*Assumptions!$B$6*Assumptions!$B$24*(1-E$4) | F8: =(Assumptions!$B$13-Assumptions!$B$10)*$A8*Assumptions!$B$6*Assumptions!$B$24*(1-F$4)
A9: 1.1 | B9: =(Assumptions!$B$13-Assumptions!$B$10)*$A9*Assumptions!$B$6*Assumptions!$B$24*(1-B$4) | C9: =(Assumptions!$B$13-Assumptions!$B$10)*$A9*Assumptions!$B$6*Assumptions!$B$24*(1-C$4) | D9: =(Assumptions!$B$13-Assumptions!$B$10)*$A9*Assumptions!$B$6*Assumptions!$B$24*(1-D$4) | E9: =(Assumptions!$B$13-Assumptions!$B$10)*$A9*Assumptions!$B$6*Assumptions!$B$24*(1-E$4) | F9: =(Assumptions!$B$13-Assumptions!$B$10)*$A9*Assumptions!$B$6*Assumptions!$B$24*(1-F$4)
A11: Gap-closure benefit expressed via the revenue-equivalent route (consistent with Method B).
